iotedgedev/__init__.py
iotedgedev/args.py
iotedgedev/azurecli.py
iotedgedev/buildoptionsparser.py
iotedgedev/buildprofile.py
iotedgedev/cli.py
iotedgedev/connectionstring.py
iotedgedev/constants.py
iotedgedev/containerregistry.py
iotedgedev/decorators.py
iotedgedev/deploymentmanifest.py
iotedgedev/dockercls.py
iotedgedev/dotnet.py
iotedgedev/edge.py
iotedgedev/envvars.py
iotedgedev/iothub.py
iotedgedev/module.py
iotedgedev/modules.py
iotedgedev/organizedgroup.py
iotedgedev/output.py
iotedgedev/simulator.py
iotedgedev/solution.py
iotedgedev/telemetry.py
iotedgedev/telemetryconfig.py
iotedgedev/telemetryuploader.py
iotedgedev/utility.py
iotedgedev/version.py
iotedgedev/template/.env.tmp
iotedgedev/template/.gitignore
iotedgedev/template/deployment.template.json
iotedgedev/template/launch_c.json
iotedgedev/template/launch_csharp.json
iotedgedev/template/launch_java.json
iotedgedev/template/launch_node.json
iotedgedev/template/launch_python.json
iotedgedev-3.3.7.dist-info/LICENSE
iotedgedev-3.3.7.dist-info/METADATA
iotedgedev-3.3.7.dist-info/WHEEL
iotedgedev-3.3.7.dist-info/entry_points.txt
iotedgedev-3.3.7.dist-info/top_level.txt
iotedgedev-3.3.7.dist-info/RECORD
